{"regional_info": {"oa_sa": "N00004500", "group": "7a", "area": 143217.664958, "region": "Derry and Strabane", "subgroup": "7a2", "supergroup": 7, "length": 2478.44561291, "population": 172.0}, "display_name": "65, Main Street, Townparks of Strabane, Strabane, County Tyrone, Northern Ireland, BT82 8AU, UK", "importance": "0", "extratags": {}, "place_id": "4608214", "lon": "-7.46366011582182", "osm_type": "way", "licence": "Data \u00a9 OpenStreetMap contributors, ODbL 1.0. https://www.openstreetmap.org/copyright", "osm_id": "261902328", "lat": "54.8258223", "type": "yes", "class": "building", "address": {"town": "Strabane", "locality": "Townparks of Strabane", "house_number": "65", "country": "UK", "county": "County Tyrone", "state": "Northern Ireland", "postcode": "BT82 8AU", "country_code": "gb", "road": "Main Street"}}