{"regional_info": {"oa_sa": "N00003167", "group": "1a", "area": 9880101.21618, "region": "Causeway Coast and Glens", "subgroup": "1a1", "supergroup": 1, "length": 22088.7808435, "population": 286.0}, "display_name": "37, Moneyrannel Road, Lisnakilly, Limavady, County Londonderry, Northern Ireland, BT49 0EP, UK", "importance": "0", "extratags": {}, "place_id": "4691690", "lon": "-6.97134413308132", "osm_type": "way", "licence": "Data \u00a9 OpenStreetMap contributors, ODbL 1.0. https://www.openstreetmap.org/copyright", "osm_id": "277906559", "lat": "55.0509755", "type": "yes", "class": "building", "address": {"town": "Limavady", "locality": "Lisnakilly", "house_number": "37", "country": "UK", "county": "County Londonderry", "state": "Northern Ireland", "postcode": "BT49 0EP", "country_code": "gb", "road": "Moneyrannel Road"}}