{"regional_info": {"oa_sa": "N00003415", "group": "8b", "area": 86216.3609579, "region": "Lisburn and Castlereagh", "subgroup": "8b2", "supergroup": 8, "length": 2595.30402074, "population": 309.0}, "display_name": "2, Drumard Grange, Ballymacoss, Lisburn, County Antrim, Northern Ireland, BT28 2SA, UK", "importance": "0", "extratags": {}, "place_id": "5446555", "lon": "-6.07298862554004", "osm_type": "way", "licence": "Data \u00a9 OpenStreetMap contributors, ODbL 1.0. https://www.openstreetmap.org/copyright", "osm_id": "402164057", "lat": "54.51649905", "type": "yes", "class": "building", "address": {"city": "Lisburn", "locality": "Ballymacoss", "house_number": "2", "country": "UK", "county": "County Antrim", "state": "Northern Ireland", "postcode": "BT28 2SA", "country_code": "gb", "road": "Drumard Grange"}}