{"regional_info": {"oa_sa": "N00003522", "group": "5b", "area": 181910.576505, "region": "Lisburn and Castlereagh", "subgroup": "5b2", "supergroup": 5, "length": 2788.88392215, "population": 408.0}, "display_name": "64, Antrim Road, Tonagh, Lisburn, County Antrim, Northern Ireland, BT28 3AD, UK", "importance": "0", "extratags": {}, "place_id": "5638561", "lon": "-6.05588096071429", "osm_type": "way", "licence": "Data \u00a9 OpenStreetMap contributors, ODbL 1.0. https://www.openstreetmap.org/copyright", "osm_id": "442044269", "lat": "54.5187659", "type": "yes", "class": "building", "address": {"city": "Lisburn", "locality": "Tonagh", "house_number": "64", "country": "UK", "county": "County Antrim", "state": "Northern Ireland", "postcode": "BT28 3AD", "country_code": "gb", "road": "Antrim Road"}}