{"regional_info": {"oa_sa": "N00003407", "group": "6b", "area": 516129.316406, "region": "Lisburn and Castlereagh", "subgroup": "6b2", "supergroup": 6, "length": 3668.21074633, "population": 558.0}, "display_name": "26, Mornington Avenue, Mornington, Knockmore, Lisburn, County Antrim, Northern Ireland, BT28 2EX, UK", "importance": "0", "extratags": {}, "place_id": "5675349", "lon": "-6.08299313926003", "osm_type": "way", "licence": "Data \u00a9 OpenStreetMap contributors, ODbL 1.0. https://www.openstreetmap.org/copyright", "osm_id": "449535850", "lat": "54.51153275", "type": "yes", "class": "building", "address": {"city": "Lisburn", "locality": "Knockmore", "house_number": "26", "residential": "Mornington", "county": "County Antrim", "state": "Northern Ireland", "postcode": "BT28 2EX", "country_code": "gb", "country": "UK", "road": "Mornington Avenue"}}