{"regional_info": {"oa_sa": "N00003363", "group": "8c", "area": 90505.1476359, "region": "Lisburn and Castlereagh", "subgroup": "8c1", "supergroup": 8, "length": 2142.5656185, "population": 706.0}, "display_name": "15, Ferndell, Magheralave, Lisburn, County Antrim, Northern Ireland, BT27 4HT, UK", "importance": "0", "extratags": {}, "place_id": "5823125", "lon": "-6.03767188964475", "osm_type": "way", "licence": "Data \u00a9 OpenStreetMap contributors, ODbL 1.0. https://www.openstreetmap.org/copyright", "osm_id": "480219384", "lat": "54.52468625", "type": "yes", "class": "building", "address": {"city": "Lisburn", "locality": "Magheralave", "house_number": "15", "country": "UK", "county": "County Antrim", "state": "Northern Ireland", "postcode": "BT27 4HT", "country_code": "gb", "road": "Ferndell"}}