{"regional_info": {"oa_sa": "N00003941", "group": "1a", "area": 5046205.75323, "region": "Antrim and Newtownabbey", "subgroup": "1a1", "supergroup": 1, "length": 21262.7693942, "population": 379.0}, "display_name": "44, Kingsmoss Road, Kingsbog, Ballyrobert, County Antrim, Northern Ireland, BT36 4SU, UK", "importance": "0", "extratags": {}, "place_id": "5874899", "lon": "-5.98934920535547", "osm_type": "way", "licence": "Data \u00a9 OpenStreetMap contributors, ODbL 1.0. https://www.openstreetmap.org/copyright", "osm_id": "492151253", "lat": "54.70959545", "type": "yes", "class": "building", "address": {"locality": "Kingsbog", "house_number": "44", "country": "UK", "county": "County Antrim", "state": "Northern Ireland", "postcode": "BT36 4SU", "country_code": "gb", "village": "Ballyrobert", "road": "Kingsmoss Road"}}