{"regional_info": {"oa_sa": "N00003307", "group": "5a", "area": 573840.393025, "region": "Lisburn and Castlereagh", "subgroup": "5a1", "supergroup": 5, "length": 6448.51888316, "population": 562.0}, "display_name": "47, Ridge Park, Derryaghy, Milltown, County Antrim, Northern Ireland, BT28 3SQ, UK", "importance": "0", "extratags": {}, "place_id": "5954574", "lon": "-6.0474267129041", "osm_type": "way", "licence": "Data \u00a9 OpenStreetMap contributors, ODbL 1.0. https://www.openstreetmap.org/copyright", "osm_id": "509843417", "lat": "54.5432475", "type": "yes", "class": "building", "address": {"locality": "Derryaghy", "house_number": "47", "country": "UK", "county": "County Antrim", "state": "Northern Ireland", "postcode": "BT28 3SQ", "country_code": "gb", "village": "Milltown", "road": "Ridge Park"}}