{"regional_info": {"oa_sa": "N00003371", "group": "7a", "area": 418829.203033, "region": "Lisburn and Castlereagh", "subgroup": "7a2", "supergroup": 7, "length": 3771.67790645, "population": 321.0}, "display_name": "1, Nicholson Gardens, Old Warren, Lisburn, County Antrim, Northern Ireland, BT28 1JL, UK", "importance": "0", "extratags": {}, "place_id": "5962227", "lon": "-6.04497974314198", "osm_type": "way", "licence": "Data \u00a9 OpenStreetMap contributors, ODbL 1.0. https://www.openstreetmap.org/copyright", "osm_id": "511769799", "lat": "54.50747355", "type": "yes", "class": "building", "address": {"city": "Lisburn", "locality": "Old Warren", "house_number": "1", "country": "UK", "county": "County Antrim", "state": "Northern Ireland", "postcode": "BT28 1JL", "country_code": "gb", "road": "Nicholson Gardens"}}