{"regional_info": {"oa_sa": "N00000555", "group": "8d", "area": 56723.8606945, "region": "Mid and East Antrim", "subgroup": "8d3", "supergroup": 8, "length": 1292.60091573, "population": 251.0}, "display_name": "9, Hawthorne Park, Dunclug, Ballymena, County Antrim, Northern Ireland, BT43 6HB, UK", "importance": "0", "extratags": {}, "place_id": "6025688", "lon": "-6.27034923988849", "osm_type": "way", "licence": "Data \u00a9 OpenStreetMap contributors, ODbL 1.0. https://www.openstreetmap.org/copyright", "osm_id": "530576965", "lat": "54.8797065", "type": "yes", "class": "building", "address": {"town": "Ballymena", "locality": "Dunclug", "house_number": "9", "residential": "Hawthorne Park", "county": "County Antrim", "state": "Northern Ireland", "postcode": "BT43 6HB", "country_code": "gb", "country": "UK", "road": "Hawthorne Park"}}