{"regional_info": {"oa_sa": "N00003486", "group": "7a", "area": 62428.8319459, "region": "Lisburn and Castlereagh", "subgroup": "7a1", "supergroup": 7, "length": 1479.83557226, "population": 355.0}, "display_name": "90, Tirowen Drive, Knockmore, Lisburn, County Antrim, Northern Ireland, BT28 2SA, UK", "importance": "0", "extratags": {}, "place_id": "6135614", "lon": "-6.0771747582025", "osm_type": "way", "licence": "Data \u00a9 OpenStreetMap contributors, ODbL 1.0. https://www.openstreetmap.org/copyright", "osm_id": "561520050", "lat": "54.50949035", "type": "yes", "class": "building", "address": {"city": "Lisburn", "locality": "Knockmore", "house_number": "90", "country": "UK", "county": "County Antrim", "state": "Northern Ireland", "postcode": "BT28 2SA", "country_code": "gb", "road": "Tirowen Drive"}}